{
    "lockfile_version": 1,
    "core": {
        "cms": {
            "type": "core",
            "id": "cms",
            "package": "radaptor/core/cms",
            "source": {
                "registry": "default",
                "resolved_registry_url": "https://packages.radaptor.com/registry.json",
                "type": "registry",
                "version": "^0.1.0"
            },
            "resolved": {
                "dist_sha256": "e2c5413d653c6a4c475a5af9923a7a058bfdc4e91e77b3b29d4784869bf97640",
                "dist_url": "https://packages.radaptor.com/packages/radaptor-core-cms/0.1.42/package.zip",
                "path": "packages/registry/core/cms",
                "registry": "default",
                "registry_url": "https://packages.radaptor.com/registry.json",
                "type": "registry",
                "version": "0.1.42"
            },
            "dependencies": {
                "radaptor/core/framework": "^0.1.36"
            },
            "composer": {
                "require": {
                    "ext-curl": "*",
                    "php": "^8.5"
                }
            }
        },
        "framework": {
            "type": "core",
            "id": "framework",
            "package": "radaptor/core/framework",
            "source": {
                "registry": "default",
                "resolved_registry_url": "https://packages.radaptor.com/registry.json",
                "type": "registry",
                "version": "^0.1.0"
            },
            "resolved": {
                "dist_sha256": "ba93c7dfcb48cd9f3d9e482855192c61af0f6bba81bc1dc0ce544683d4179ea5",
                "dist_url": "https://packages.radaptor.com/packages/radaptor-core-framework/0.1.38/package.zip",
                "path": "packages/registry/core/framework",
                "registry": "default",
                "registry_url": "https://packages.radaptor.com/registry.json",
                "type": "registry",
                "version": "0.1.38"
            },
            "dependencies": [],
            "composer": {
                "require": {
                    "php": "^8.5"
                }
            }
        }
    },
    "themes": {
        "portal-admin": {
            "type": "theme",
            "id": "portal-admin",
            "package": "radaptor/themes/portal-admin",
            "source": {
                "registry": "default",
                "resolved_registry_url": "https://packages.radaptor.com/registry.json",
                "type": "registry",
                "version": "^0.1.0"
            },
            "resolved": {
                "dist_sha256": "4ac5fa9fc5f50dfe65881b2927e6c3008599c4ea66fd83e701a83176b5391a0a",
                "dist_url": "https://packages.radaptor.com/packages/radaptor-themes-portal-admin/0.1.18/package.zip",
                "path": "packages/registry/themes/portal-admin",
                "registry": "default",
                "registry_url": "https://packages.radaptor.com/registry.json",
                "type": "registry",
                "version": "0.1.18"
            },
            "dependencies": {
                "radaptor/core/cms": "^0.1.31"
            },
            "composer": {
                "require": {
                    "php": "^8.5"
                }
            },
            "assets": {
                "public": [
                    {
                        "source": "public/assets/radaptor-portal-admin",
                        "target": "assets/packages/radaptor-portal-admin"
                    },
                    {
                        "source": "public/assets/themes/radaptor-portal-admin",
                        "target": "assets/packages/themes/radaptor-portal-admin"
                    }
                ]
            }
        }
    }
}
